[[
  "1",
  "2",
  "3"
],{
  "id": "4",
  "name": "5",
  "bookings": "6"
},{
  "id": "7",
  "name": "8",
  "bookings": "9"
},{
  "id": "10",
  "name": "11",
  "bookings": "12"
},"1c1d2255-ae96-4da0-a017-c2ad370347d1","Yesim",[
  "13",
  "14"
],"0187b207-7b31-4642-8124-6e53427355e3","Betul",[
  "15"
],"0082c20b-633c-41f7-b6ec-ff2bb26a309c","new surfer",[],{
  "surfer": "16",
  "host": "17",
  "origin": "18",
  "duration": "19"
},{
  "surfer": "16",
  "host": "20",
  "origin": "21",
  "duration": "22"
},{
  "surfer": "23",
  "origin": "18",
  "duration": "19"
},{
  "id": "4",
  "name": "5",
  "bookings": "6"
},{
  "id": "24",
  "name": "25",
  "location": "18"
},"Leipzig","3 days",{
  "id": "26",
  "name": "27",
  "location": "21"
},"Berlin","2 days",{
  "id": "7",
  "name": "8",
  "bookings": "9"
},"2895e3e9-a854-495a-a7c0-cd5ae78310e1","Nihal","c6b3b6bd-2067-4b8c-a473-12cc8c1655ba","David"]